AUTHORS
LICENSE
MANIFEST.in
README.rst
setup.py
thunderclient/__init__.py
thunderclient.egg-info/PKG-INFO
thunderclient.egg-info/SOURCES.txt
thunderclient.egg-info/dependency_links.txt
thunderclient.egg-info/not-zip-safe
thunderclient.egg-info/requires.txt
thunderclient.egg-info/top_level.txt