Metadata-Version: 1.1
Name: thunderclient
Version: 1.0.1
Summary: A Python library for sending messages to Thunderpush server.
Home-page: https://github.com/thunderpush/python-thunderclient
Author: Krzysztof Jagiello
Author-email: me@kjagiello.com
License: BSD
Platform: UNKNOWN
Classifier: License :: OSI Approved :: BSD License
Classifier: Programming Language :: Python
Classifier: Programming Language :: Python :: 3
Classifier: Intended Audience :: Developers
Classifier: Topic :: Internet :: WWW/HTTP
